{
  "kimi": {
    "growth-factors": "/v2/cat-growth.jpg",
    "research-blends": "/v2/cat-blends.jpg",
    "lab-supplies": "/v2/cat-tissue.jpg",
    "semaglutide-5mg": "/products/semaglutide-5mg.jpg",
    "tirzepatide-5mg": "/products/tirzepatide-5mg.jpg",
    "retatrutide-5mg": "/products/retatrutide-5mg.jpg",
    "cagrilintide-5mg": "/products/cagrilintide-5mg.jpg",
    "sermorelin-5mg": "/products/sermorelin-5mg.jpg",
    "tesamorelin-5mg": "/products/tesamorelin-5mg.jpg",
    "cjc1295-dac-5mg": "/products/cjc1295-5mg.jpg",
    "cjc1295-nodac-5mg": "/products/cjc1295-5mg.jpg",
    "ipamorelin-5mg": "/products/ipamorelin-5mg.jpg",
    "5amino1mq-5mg": "/products/5amino1mq-10mg.jpg",
    "aod9604-5mg": "/products/aod9604-5mg.jpg",
    "mazdutide-5mg": "/v2/vial-single.jpg",
    "bpc157-5mg": "/products/bpc157-5mg.jpg",
    "tb500-5mg": "/products/tb500-10mg.jpg",
    "ghk-cu-50mg": "/products/ghk-cu-100mg.jpg",
    "bpc157-tb500-blend": "/products/blend-bpc157-tb500.jpg",
    "cjc-ipamorelin-blend": "/v2/cat-blends.jpg",
    "bac-water-3ml": "/products/bac-water-10ml.png",
    "acetic-acid-3ml": "/products/acetic-acid-3ml.png",
    "mk677-5mg": "/products/mk677-5mg.jpg",
    "melanotan2-10mg": "/products/melanotan2-10mg.jpg",
    "ghk-cu-100mg": "/products/ghk-cu-100mg.jpg",
    "hgh-10iu": "/products/hgh-10iu.jpg",
    "nad-plus-100mg": "/products/nad-plus-500mg.jpg",
    "glutathione-600mg": "/products/glutathione-600mg.jpg",
    "ll37-5mg": "/products/ll37-5mg.jpg",
    "epithalon-10mg": "/products/epithalon-10mg.jpg",
    "dsip-5mg": "/products/dsip-5mg.jpg",
    "selank-5mg": "/products/selank-5mg.jpg",
    "semax-5mg": "/products/semax-5mg.jpg",
    "thymosin-5mg": "/products/thymosin-5mg.jpg",
    "vip-10mg": "/products/vip-10mg.jpg",
    "bremelanotide-10mg": "/products/bremelanotide-10mg.jpg",
    "hcg-5000iu": "/products/hcg-5000iu.jpg",
    "igf1-lr3-1mg": "/products/igf1-lr3-1mg.jpg",
    "bpc157-caps": "/products/bpc-157-capsules.png",
    "pinealon-caps": "/products/pinealon-capsules.png"
  },
  "aliases": {
    "acetic-acid-water": {
      "slug": "acetic-acid-3ml",
      "image": "/products/acetic-acid-3ml.png"
    },
    "acetic-acid-water-3ml": {
      "slug": "acetic-acid-3ml",
      "image": "/products/acetic-acid-3ml.png"
    },
    "bacteriostatic-water": {
      "slug": "bac-water-3ml",
      "image": "/products/bac-water-10ml.png"
    },
    "bacteriostatic-water-3ml": {
      "slug": "bac-water-3ml",
      "image": "/products/bac-water-10ml.png"
    },
    "bacteriostatic-water-10ml": {
      "slug": "bac-water-3ml",
      "image": "/products/bac-water-10ml.png"
    },
    "5-amino-1mq": {
      "slug": "5amino1mq-5mg",
      "image": "/products/5amino1mq-10mg.jpg"
    },
    "5-amino-1mq-5mg": {
      "slug": "5amino1mq-5mg",
      "image": "/products/5amino1mq-10mg.jpg"
    },
    "5-amino-1mq-10mg": {
      "slug": "5amino1mq-5mg",
      "image": "/products/5amino1mq-10mg.jpg"
    },
    "aod-9604": {
      "slug": "aod9604-5mg",
      "image": "/products/aod9604-5mg.jpg"
    },
    "aod-9604-5mg": {
      "slug": "aod9604-5mg",
      "image": "/products/aod9604-5mg.jpg"
    },
    "aod-9604-10mg": {
      "slug": "aod9604-5mg",
      "image": "/products/aod9604-5mg.jpg"
    },
    "cagrilintide": {
      "slug": "cagrilintide-5mg",
      "image": "/products/cagrilintide-5mg.jpg"
    },
    "cagrilintide-5mg": {
      "slug": "cagrilintide-5mg",
      "image": "/products/cagrilintide-5mg.jpg"
    },
    "cagrilintide-10mg": {
      "slug": "cagrilintide-5mg",
      "image": "/products/cagrilintide-5mg.jpg"
    },
    "cagrilintide-semaglutide": {
      "slug": "blend-bpc157-tb500",
      "image": "/products/blend-bpc157-tb500.jpg"
    },
    "retatrutide": {
      "slug": "retatrutide-5mg",
      "image": "/products/retatrutide-5mg.jpg"
    },
    "retatrutide-5mg": {
      "slug": "retatrutide-5mg",
      "image": "/products/retatrutide-5mg.jpg"
    },
    "semaglutide": {
      "slug": "semaglutide-5mg",
      "image": "/products/semaglutide-5mg.jpg"
    },
    "semaglutide-5mg": {
      "slug": "semaglutide-5mg",
      "image": "/products/semaglutide-5mg.jpg"
    },
    "sermorelin": {
      "slug": "sermorelin-5mg",
      "image": "/products/sermorelin-5mg.jpg"
    },
    "sermorelin-5mg": {
      "slug": "sermorelin-5mg",
      "image": "/products/sermorelin-5mg.jpg"
    },
    "sermorelin-10mg": {
      "slug": "sermorelin-5mg",
      "image": "/products/sermorelin-5mg.jpg"
    },
    "tesamorelin": {
      "slug": "tesamorelin-5mg",
      "image": "/products/tesamorelin-5mg.jpg"
    },
    "tesamorelin-5mg": {
      "slug": "tesamorelin-5mg",
      "image": "/products/tesamorelin-5mg.jpg"
    },
    "tirzepatide": {
      "slug": "tirzepatide-5mg",
      "image": "/products/tirzepatide-5mg.jpg"
    },
    "tirzepatide-5mg": {
      "slug": "tirzepatide-5mg",
      "image": "/products/tirzepatide-5mg.jpg"
    },
    "bpc-157": {
      "slug": "bpc157-5mg",
      "image": "/products/bpc157-5mg.jpg"
    },
    "bpc-157-5mg": {
      "slug": "bpc157-5mg",
      "image": "/products/bpc157-5mg.jpg"
    },
    "bpc-157-10mg": {
      "slug": "bpc157-5mg",
      "image": "/products/bpc157-5mg.jpg"
    },
    "bpc-157-capsules": {
      "slug": "bpc-157-capsules",
      "image": "/products/bpc-157-capsules.png"
    },
    "bpc-157-capsules-100ct": {
      "slug": "bpc-157-capsules",
      "image": "/products/bpc-157-capsules.png"
    },
    "tb500": {
      "slug": "tb500-5mg",
      "image": "/products/tb500-10mg.jpg"
    },
    "tb500-5mg": {
      "slug": "tb500-5mg",
      "image": "/products/tb500-10mg.jpg"
    },
    "tb500-10mg": {
      "slug": "tb500-5mg",
      "image": "/products/tb500-10mg.jpg"
    },
    "bpc-157-5mg-tb500-5mg": {
      "slug": "bpc157-tb500-blend",
      "image": "/products/blend-bpc157-tb500.jpg"
    },
    "glow-blend-30mg": {
      "slug": "bpc157-tb500-blend",
      "image": "/products/blend-bpc157-tb500.jpg"
    },
    "glow-blend-85mg": {
      "slug": "bpc157-tb500-blend",
      "image": "/products/blend-bpc157-tb500.jpg"
    },
    "glow-bpc-157-tb500-ghk-cu": {
      "slug": "bpc157-tb500-blend",
      "image": "/products/blend-bpc157-tb500.jpg"
    },
    "glow-tb500-10mg-bpc-157-10mg-ghk-cu-50mg": {
      "slug": "bpc157-tb500-blend",
      "image": "/products/blend-bpc157-tb500.jpg"
    },
    "glow-tb500-10mg-bpc-157-10mg-ghk-cu-50mg-70mg": {
      "slug": "bpc157-tb500-blend",
      "image": "/products/blend-bpc157-tb500.jpg"
    },
    "cjc-1295-with-dac": {
      "slug": "cjc1295-dac-5mg",
      "image": "/products/cjc1295-5mg.jpg"
    },
    "cjc-1295-with-dac-5mg": {
      "slug": "cjc1295-dac-5mg",
      "image": "/products/cjc1295-5mg.jpg"
    },
    "cjc-1295-without-dac": {
      "slug": "cjc1295-nodac-5mg",
      "image": "/products/cjc1295-5mg.jpg"
    },
    "cjc-1295-without-dac-5mg": {
      "slug": "cjc1295-nodac-5mg",
      "image": "/products/cjc1295-5mg.jpg"
    },
    "cjc-1295-without-dac-ipamorelin-blend": {
      "slug": "cjc1295-nodac-5mg",
      "image": "/products/cjc1295-5mg.jpg"
    },
    "cjc-1295-without-dac-sermorelin-ipamorelin-blend": {
      "slug": "cjc1295-nodac-5mg",
      "image": "/products/cjc1295-5mg.jpg"
    },
    "ipamorelin": {
      "slug": "ipamorelin-5mg",
      "image": "/products/ipamorelin-5mg.jpg"
    },
    "ipamorelin-5mg": {
      "slug": "ipamorelin-5mg",
      "image": "/products/ipamorelin-5mg.jpg"
    },
    "hcg": {
      "slug": "hcg-5000iu",
      "image": "/products/hcg-5000iu.jpg"
    },
    "hcg-5000-iu": {
      "slug": "hcg-5000iu",
      "image": "/products/hcg-5000iu.jpg"
    },
    "hgh-191aa": {
      "slug": "hgh-10iu",
      "image": "/products/hgh-10iu.jpg"
    },
    "hgh-191aa-10-iu": {
      "slug": "hgh-10iu",
      "image": "/products/hgh-10iu.jpg"
    },
    "igf-1-lr3": {
      "slug": "igf1-lr3-1mg",
      "image": "/products/igf1-lr3-1mg.jpg"
    },
    "igf-1-lr3-1mg": {
      "slug": "igf1-lr3-1mg",
      "image": "/products/igf1-lr3-1mg.jpg"
    },
    "ghk-cu": {
      "slug": "ghk-cu-50mg",
      "image": "/products/ghk-cu-100mg.jpg"
    },
    "ghk-cu-50mg": {
      "slug": "ghk-cu-50mg",
      "image": "/products/ghk-cu-100mg.jpg"
    },
    "ghk-cu-100mg": {
      "slug": "ghk-cu-100mg",
      "image": "/products/ghk-cu-100mg.jpg"
    },
    "melanotan-2": {
      "slug": "melanotan2-10mg",
      "image": "/products/melanotan2-10mg.jpg"
    },
    "melanotan-2-10mg": {
      "slug": "melanotan2-10mg",
      "image": "/products/melanotan2-10mg.jpg"
    },
    "bremelanotide": {
      "slug": "bremelanotide-10mg",
      "image": "/products/bremelanotide-10mg.jpg"
    },
    "bremelanotide-10mg": {
      "slug": "bremelanotide-10mg",
      "image": "/products/bremelanotide-10mg.jpg"
    },
    "dsip": {
      "slug": "dsip-5mg",
      "image": "/products/dsip-5mg.jpg"
    },
    "dsip-5mg": {
      "slug": "dsip-5mg",
      "image": "/products/dsip-5mg.jpg"
    },
    "epithalon": {
      "slug": "epithalon-10mg",
      "image": "/products/epithalon-10mg.jpg"
    },
    "epithalon-10mg": {
      "slug": "epithalon-10mg",
      "image": "/products/epithalon-10mg.jpg"
    },
    "ll-37": {
      "slug": "ll37-5mg",
      "image": "/products/ll37-5mg.jpg"
    },
    "ll-37-5mg": {
      "slug": "ll37-5mg",
      "image": "/products/ll37-5mg.jpg"
    },
    "nad": {
      "slug": "nad-plus-100mg",
      "image": "/products/nad-plus-500mg.jpg"
    },
    "nad-plus-100mg": {
      "slug": "nad-plus-100mg",
      "image": "/products/nad-plus-500mg.jpg"
    },
    "nad-plus-500mg": {
      "slug": "nad-plus-500mg",
      "image": "/products/nad-plus-500mg.jpg"
    },
    "selank": {
      "slug": "selank-5mg",
      "image": "/products/selank-5mg.jpg"
    },
    "selank-5mg": {
      "slug": "selank-5mg",
      "image": "/products/selank-5mg.jpg"
    },
    "semax": {
      "slug": "semax-5mg",
      "image": "/products/semax-5mg.jpg"
    },
    "semax-5mg": {
      "slug": "semax-5mg",
      "image": "/products/semax-5mg.jpg"
    },
    "thymosin-alpha-1": {
      "slug": "thymosin-5mg",
      "image": "/products/thymosin-5mg.jpg"
    },
    "thymosin-alpha-1-5mg": {
      "slug": "thymosin-5mg",
      "image": "/products/thymosin-5mg.jpg"
    },
    "vip": {
      "slug": "vip-10mg",
      "image": "/products/vip-10mg.jpg"
    },
    "vip-10mg": {
      "slug": "vip-10mg",
      "image": "/products/vip-10mg.jpg"
    },
    "glutathione": {
      "slug": "glutathione-600mg",
      "image": "/products/glutathione-600mg.jpg"
    },
    "glutathione-600mg": {
      "slug": "glutathione-600mg",
      "image": "/products/glutathione-600mg.jpg"
    },
    "mk-677": {
      "slug": "mk677-5mg",
      "image": "/products/mk677-5mg.jpg"
    },
    "mk-677-5mg": {
      "slug": "mk677-5mg",
      "image": "/products/mk677-5mg.jpg"
    },
    "pinealon-capsules": {
      "slug": "pinealon-capsules",
      "image": "/products/pinealon-capsules.png"
    },
    "pinealon-capsules-100-count": {
      "slug": "pinealon-capsules",
      "image": "/products/pinealon-capsules.png"
    }
  }
}